{
  "meta": {
    "updated_at": "2026-02-20 20:40:04",
    "focus_message": "",
    "sync_success": true
  },
  "focus_view_model": [
    {
      "ticker": "W",
      "verdict": "HIGH_RVOL_EVENT",
      "urgency": 96,
      "signal": "Break SMA200 \u00b7 confirm=3d \u00b7 signals=4",
      "news": "\ud83d\udfe5\ud83d\udfe5 -0.20",
      "news_sentiment_raw": -0.2,
      "volume_alert": true,
      "trend_color": "RED",
      "news_headline": "Wayfair reported Q4/FY2025 results (6.9% YoY Q4 revenue growth) while Stifel maintained Hold and cut its target to $89. ([investor.wayfair.com][1])",
      "news_age": "1d",
      "news_sources": 2,
      "news_summary": "Wayfair disclosed Q4 net revenue of about $3.3B with continued share capture, but same-day analyst follow-through included a Hold reiteration and price-target cut, which keeps post-earnings sentiment mixed. ([investor.wayfair.com][1])",
      "reason": "",
      "logic_pillars": {
        "technical": "F1: LatestPrice=79.57 (type=Close, asof=2026-02-19) remains deeply below F2 SMA200=102.02 and F5 EMA21=94.26; F3 confirms DOWNTREND.",
        "volume_analysis": "V1 RVOL20=2.82 is the strongest anomaly in the set and signals institutional-conviction trading; this is not a quiet drift.",
        "news_catalyst": "N1 unavailable; see external_intel for mixed post-earnings/rating pressure (results + target cut)."
      },
      "divergence": "F6 SA Overall=Hold is consistent with the mixed external setup, but the unusually large V1 spike means this name deserves immediate tape-level monitoring for either capitulation or base formation.",
      "action_plan": "Do not front-run. Require a reclaim of F5 EMA21=94.26 before treating this as a durable reversal; until then, treat rallies as suspect under M5 RISK_OFF.",
      "break_confirm_days": 3.0,
      "trigger_count": 4.0,
      "primary_trigger_key": "BREAK_SMA200",
      "trigger_details": {
        "trigger_type": "Break SMA200 \u00b7 confirm=3d \u00b7 signals=4",
        "current_price": 79.56999969482422,
        "key_level": "EMA21: $94.26 (-15.6%)",
        "details": "SMA200 $102.02 (-22.0%) | EMA55 $99.40 (-19.9%) | EMA21 $94.26 (-15.6%) | Volume 2.8x average",
        "break_confirm_days": 3.0,
        "trigger_count": "4",
        "primary_trigger_key": "BREAK_SMA200"
      },
      "sector": "Unknown",
      "quant_score": 3.2,
      "last_price": 79.56999969482422,
      "day_change_pct": null,
      "picked_date": "12/1/2025",
      "indicator_asof": "2026-02-19",
      "dte": 69,
      "next_earnings": "2026-04-30",
      "dist_sma200_pct": -22.006366622467112,
      "dist_ema21_pct": -15.587005281153838,
      "dist_ema55_pct": -19.94850009522099,
      "sma200": 102.02114743092021,
      "ema55": 99.39851194477613,
      "ema21": 94.26273757950126,
      "vol_ratio": 2.817727688761951,
      "latest_price": 79.56999969482422,
      "price_type": "Close",
      "price_timestamp": "2026-02-19",
      "news_blurb": "Wayfair reported Q4/FY2025 results (6.9% YoY Q4 revenue growth) while Stifel maintained Hold and cut its target to $89. ([investor.wayfair.com][1]) \u00b7 1d \u00b7 2 src"
    },
    {
      "ticker": "SSRM",
      "verdict": "EARNINGS_MOMO",
      "urgency": 93,
      "signal": "HIGH",
      "news": "\ud83d\udfe9\ud83d\udfe9\ud83d\udfe9 +0.80",
      "news_sentiment_raw": 0.8,
      "volume_alert": true,
      "trend_color": "GREEN",
      "news_headline": "SSR Mining reported full-year 2025 results and 2026 guidance, including Q4 adjusted EPS of $0.88 and a board-approved $300M buyback. ([businesswire.com][2])",
      "news_age": "4d",
      "news_sources": 1,
      "news_summary": "The company posted strong quarterly/full-year profitability, issued 2026 operating guidance, and highlighted a $300M repurchase authorization, reinforcing a positive fundamental catalyst stack for the ongoing uptrend. ([businesswire.com][2])",
      "reason": "",
      "logic_pillars": {
        "technical": "F1: LatestPrice=29.11 (type=Close, asof=2026-02-19) is far above F2 SMA200=18.93, F4 EMA55=24.18, and F5 EMA21=25.73; F3 confirms UPTREND.",
        "volume_analysis": "V1 RVOL20=1.34 is above normal and supports the move as institutionally backed rather than purely momentum-chasing.",
        "news_catalyst": "N1 unavailable; see external_intel for earnings/guidance/buyback alignment."
      },
      "divergence": "No major divergence: F6 SA Overall=Strong Buy aligns with F3 UPTREND, positive external_intel, and supportive V1.",
      "action_plan": "Trend-follow only: maintain bullish bias while price holds above F5 EMA21=25.73; loss of F5 shifts focus to F4 EMA55=24.18 as next validation level.",
      "break_confirm_days": null,
      "trigger_count": null,
      "primary_trigger_key": null,
      "trigger_details": {
        "trigger_type": "",
        "current_price": null,
        "key_level": "N/A",
        "details": "",
        "break_confirm_days": null,
        "trigger_count": null,
        "primary_trigger_key": null
      },
      "sector": "Unknown",
      "quant_score": 4.99,
      "last_price": 29.110000610351562,
      "day_change_pct": null,
      "picked_date": "6/16/2025",
      "indicator_asof": "2026-02-19",
      "dte": 74,
      "next_earnings": "2026-05-05",
      "dist_sma200_pct": 53.757988844316316,
      "dist_ema21_pct": 13.150428082045082,
      "dist_ema55_pct": 20.40065576781273,
      "sma200": 18.932350006103515,
      "ema55": 24.17760968552272,
      "ema21": 25.726814386635795,
      "vol_ratio": 1.3444847294844033,
      "latest_price": 29.110000610351562,
      "price_type": "Close",
      "price_timestamp": "2026-02-19",
      "news_blurb": "SSR Mining reported full-year 2025 results and 2026 guidance, including Q4 adjusted EPS of $0.88 and a board-approved $300M buyback. ([businesswire.com][2]) \u00b7 4d \u00b7 1 src"
    },
    {
      "ticker": "TMUS",
      "verdict": "TREND_CONFLICT_UPG",
      "urgency": 88,
      "signal": "Break SMA200 \u00b7 confirm=5d",
      "news": "\ud83d\udfe9\ud83d\udfe9 +0.50",
      "news_sentiment_raw": 0.5,
      "volume_alert": false,
      "trend_color": "RED",
      "news_headline": "Daiwa Capital upgraded T-Mobile US from Neutral to Outperform. ([nasdaq.com][3])",
      "news_age": "1d",
      "news_sources": 1,
      "news_summary": "A fresh analyst upgrade improves sentiment, but the tape still needs to prove itself because the stock is below long-term trend resistance even while sitting above key shorter EMAs. ([nasdaq.com][3])",
      "reason": "",
      "logic_pillars": {
        "technical": "F1: LatestPrice=215.30 (type=Close, asof=2026-02-19) is below F2 SMA200=223.07 (long-term weakness) but above F4 EMA55=202.64 and F5 EMA21=204.01 (short-term strength); F3 still labels DOWNTREND.",
        "volume_analysis": "V1 RVOL20=0.65 is light, so the setup lacks institutional confirmation despite the rating catalyst.",
        "news_catalyst": "N1 unavailable; see external_intel for the Daiwa upgrade."
      },
      "divergence": "Clear cross-signal: external analyst sentiment improved, but F3 remains DOWNTREND and V1 is weak, so this is a watchlist upgrade rather than an execution trigger.",
      "action_plan": "Prefer confirmation over anticipation: require a decisive reclaim of F2 SMA200=223.07 on stronger volume before upgrading this to actionable long.",
      "break_confirm_days": 5.0,
      "trigger_count": 1.0,
      "primary_trigger_key": "BREAK_SMA200",
      "trigger_details": {
        "trigger_type": "Break SMA200 \u00b7 confirm=5d",
        "current_price": 215.3000030517578,
        "key_level": "SMA200: $223.07 (-3.5%)",
        "details": "SMA200 $223.07 (-3.5%)",
        "break_confirm_days": 5.0,
        "trigger_count": "1",
        "primary_trigger_key": "BREAK_SMA200"
      },
      "sector": "Unknown",
      "quant_score": 3.11,
      "last_price": 215.3000030517578,
      "day_change_pct": null,
      "picked_date": "9/15/2023",
      "indicator_asof": "2026-02-19",
      "dte": 62,
      "next_earnings": "2026-04-23",
      "dist_sma200_pct": -3.4845105109895047,
      "dist_ema21_pct": 5.5341000154327,
      "dist_ema55_pct": 6.248021607299331,
      "sma200": 223.07300537109376,
      "ema55": 202.6390701631347,
      "ema21": 204.00989160875355,
      "vol_ratio": 0.6500490242719069,
      "latest_price": 215.3000030517578,
      "price_type": "Close",
      "price_timestamp": "2026-02-19",
      "news_blurb": "Daiwa Capital upgraded T-Mobile US from Neutral to Outperform. ([nasdaq.com][3]) \u00b7 1d \u00b7 1 src"
    },
    {
      "ticker": "TWLO",
      "verdict": "SENTIMENT_COLLISION",
      "urgency": 85,
      "signal": "Break SMA200 \u00b7 confirm=2d \u00b7 signals=3",
      "news": "\ud83d\udfe9\ud83d\udfe9\ud83d\udfe9 +0.60",
      "news_sentiment_raw": 0.6,
      "volume_alert": false,
      "trend_color": "RED",
      "news_headline": "Twilio was upgraded by Argus to Strong-Buy, with reports also highlighting a Q4 beat and stronger Q1 EPS guidance. ([MarketBeat][4])",
      "news_age": "0d",
      "news_sources": 1,
      "news_summary": "Analyst sentiment turned more constructive and recent reported fundamentals were better than expected, but price has not yet reclaimed long-term trend levels, creating a classic sentiment-vs-chart conflict. ([MarketBeat][4])",
      "reason": "",
      "logic_pillars": {
        "technical": "F1: LatestPrice=110.96 (type=Close, asof=2026-02-19) is below F2 SMA200=118.54, F4 EMA55=122.56, and F5 EMA21=117.16; F3 remains DOWNTREND.",
        "volume_analysis": "V1 RVOL20=0.52 is weak; any upside narrative is under-confirmed by participation.",
        "news_catalyst": "N1 unavailable; see external_intel for the analyst upgrade / positive earnings tone."
      },
      "divergence": "This is the cleanest sentiment collision in the list: positive external_intel and improving analyst tone vs F3 DOWNTREND and low-conviction V1.",
      "action_plan": "Wait for confirmation. First trigger is reclaim of F5 EMA21=117.16; higher-quality trigger is a volume-backed break above F2 SMA200=118.54.",
      "break_confirm_days": 2.0,
      "trigger_count": 3.0,
      "primary_trigger_key": "BREAK_SMA200",
      "trigger_details": {
        "trigger_type": "Break SMA200 \u00b7 confirm=2d \u00b7 signals=3",
        "current_price": 110.95999908447266,
        "key_level": "EMA21: $117.16 (-5.3%)",
        "details": "SMA200 $118.54 (-6.4%) | EMA55 $122.56 (-9.5%) | EMA21 $117.16 (-5.3%)",
        "break_confirm_days": 2.0,
        "trigger_count": "3",
        "primary_trigger_key": "BREAK_SMA200"
      },
      "sector": "Unknown",
      "quant_score": 2.94,
      "last_price": 110.95999908447266,
      "day_change_pct": null,
      "picked_date": "2/1/2024",
      "indicator_asof": "2026-02-19",
      "dte": 69,
      "next_earnings": "2026-04-30",
      "dist_sma200_pct": -6.392295466892474,
      "dist_ema21_pct": -5.2885204793114235,
      "dist_ema55_pct": -9.46207339405409,
      "sma200": 118.53725036621094,
      "ema55": 122.55637305171683,
      "ema21": 117.15580798232044,
      "vol_ratio": 0.5173131168505363,
      "latest_price": 110.95999908447266,
      "price_type": "Close",
      "price_timestamp": "2026-02-19",
      "news_blurb": "Twilio was upgraded by Argus to Strong-Buy, with reports also highlighting a Q4 beat and stronger Q1 EPS guidance. ([MarketBeat][4]) \u00b7 0d \u00b7 1 src"
    },
    {
      "ticker": "APP",
      "verdict": "SENTIMENT_COLLISION",
      "urgency": 83,
      "signal": "Break SMA200 \u00b7 confirm=3d \u00b7 signals=3",
      "news": "\ud83d\udfe9\ud83d\udfe9 +0.30",
      "news_sentiment_raw": 0.3,
      "volume_alert": false,
      "trend_color": "RED",
      "news_headline": "AppLovin shares rose on analyst upgrades/target hikes (including Wedbush and Morgan Stanley target increases cited in coverage). ([MarketBeat][5])",
      "news_age": "7d",
      "news_sources": 1,
      "news_summary": "Analyst-side sentiment remains constructive with multiple target increases, but the stock\u2019s technical damage is severe, so this is a high-volatility re-rating battle rather than a confirmed recovery. ([MarketBeat][5])",
      "reason": "",
      "logic_pillars": {
        "technical": "F1: LatestPrice=412.00 (type=Close, asof=2026-02-19) is below F2 SMA200=505.68, F4 EMA55=535.13, and F5 EMA21=462.01; F3 confirms DOWNTREND.",
        "volume_analysis": "V1 RVOL20=0.76 is below average, so the recent stabilization lacks strong institutional-accumulation evidence.",
        "news_catalyst": "N1 unavailable; see external_intel for analyst-upgrade support."
      },
      "divergence": "F6 SA Overall=Hold plus deep technical breakdown (F2/F4/F5) conflicts with still-bullish analyst tone in external_intel, making this a fragile narrative-driven watch.",
      "action_plan": "No aggressive entry while below F5 EMA21=462.01. A reclaim of F5 is the minimum condition before reassessing for mean-reversion vs trend-continuation risk.",
      "break_confirm_days": 3.0,
      "trigger_count": 3.0,
      "primary_trigger_key": "BREAK_SMA200",
      "trigger_details": {
        "trigger_type": "Break SMA200 \u00b7 confirm=3d \u00b7 signals=3",
        "current_price": 412.0,
        "key_level": "EMA21: $462.01 (-10.8%)",
        "details": "SMA200 $505.68 (-18.5%) | EMA55 $535.13 (-23.0%) | EMA21 $462.01 (-10.8%)",
        "break_confirm_days": 3.0,
        "trigger_count": "3",
        "primary_trigger_key": "BREAK_SMA200"
      },
      "sector": "Unknown",
      "quant_score": 3.26,
      "last_price": 412.0,
      "day_change_pct": null,
      "picked_date": "11/15/2023",
      "indicator_asof": "2026-02-19",
      "dte": 75,
      "next_earnings": "2026-05-06",
      "dist_sma200_pct": -18.525404802863637,
      "dist_ema21_pct": -10.824896223626254,
      "dist_ema55_pct": -23.00908006024922,
      "sma200": 505.67910034179687,
      "ema55": 535.1280388939507,
      "ema21": 462.01235832949624,
      "vol_ratio": 0.7595705001555155,
      "latest_price": 412.0,
      "price_type": "Close",
      "price_timestamp": "2026-02-19",
      "news_blurb": "AppLovin shares rose on analyst upgrades/target hikes (including Wedbush and Morgan Stanley target increases cited in coverage). ([MarketBeat][5]) \u00b7 7d \u00b7 1 src"
    },
    {
      "ticker": "UBER",
      "verdict": "RATING_PRESSURE",
      "urgency": 80,
      "signal": "Break SMA200 \u00b7 confirm=5d \u00b7 signals=3",
      "news": "\ud83d\udfe5\ud83d\udfe5 -0.40",
      "news_sentiment_raw": -0.4,
      "volume_alert": false,
      "trend_color": "RED",
      "news_headline": "Guggenheim cut Uber\u2019s price target to $125 from $135 while maintaining Buy, citing valuation/multiple concerns. ([Investing.com][6])",
      "news_age": "2d",
      "news_sources": 1,
      "news_summary": "The rating stance stayed constructive, but the target cut and valuation commentary signal moderation in upside expectations; the same report also referenced strategic moves (Getir deal, expansion impacts) that keep execution complexity elevated. ([Investing.com][6])",
      "reason": "",
      "logic_pillars": {
        "technical": "F1: LatestPrice=72.94 (type=Close, asof=2026-02-19) sits below F2 SMA200=88.88, F4 EMA55=80.78, and F5 EMA21=75.85; F3 remains DOWNTREND.",
        "volume_analysis": "V1 RVOL20=0.65 is muted, so current weakness is not showing strong capitulation or strong accumulation.",
        "news_catalyst": "N1 unavailable; see external_intel for analyst target-cut pressure."
      },
      "divergence": "F6 SA Overall=Hold fits the setup: external sentiment is not outright bearish but is being tempered by valuation concerns while the chart remains weak.",
      "action_plan": "Stay in recovery-watch mode only. Reclaim of F5 EMA21=75.85 is the first technical repair signal; stronger confirmation comes with F4 EMA55=80.78.",
      "break_confirm_days": 5.0,
      "trigger_count": 3.0,
      "primary_trigger_key": "BREAK_SMA200",
      "trigger_details": {
        "trigger_type": "Break SMA200 \u00b7 confirm=5d \u00b7 signals=3",
        "current_price": 72.94000244140625,
        "key_level": "EMA21: $75.85 (-3.8%)",
        "details": "SMA200 $88.88 (-17.9%) | EMA55 $80.78 (-9.7%) | EMA21 $75.85 (-3.8%)",
        "break_confirm_days": 5.0,
        "trigger_count": "3",
        "primary_trigger_key": "BREAK_SMA200"
      },
      "sector": "Unknown",
      "quant_score": 3.07,
      "last_price": 72.94000244140625,
      "day_change_pct": null,
      "picked_date": "6/1/2023",
      "indicator_asof": "2026-02-19",
      "dte": 75,
      "next_earnings": "2026-05-06",
      "dist_sma200_pct": -17.932859751441,
      "dist_ema21_pct": -3.8341864254540754,
      "dist_ema55_pct": -9.710185140585255,
      "sma200": 88.87845027923584,
      "ema55": 80.78430834638112,
      "ema21": 75.84816238762909,
      "vol_ratio": 0.649452640237177,
      "latest_price": 72.94000244140625,
      "price_type": "Close",
      "price_timestamp": "2026-02-19",
      "news_blurb": "Guggenheim cut Uber\u2019s price target to $125 from $135 while maintaining Buy, citing valuation/multiple concerns. ([Investing.com][6]) \u00b7 2d \u00b7 1 src"
    },
    {
      "ticker": "WLDN",
      "verdict": "EVENT_WINDOW",
      "urgency": 79,
      "signal": "Earnings 7D",
      "news": "\ud83d\udfe8 +0.00",
      "news_sentiment_raw": 0.0,
      "volume_alert": false,
      "trend_color": "GREEN",
      "news_headline": "Willdan will release Q4/FY2025 results after market close on February 26, 2026 (conference call at 5:30 p.m. ET). ([businesswire.com][7])",
      "news_age": "21d",
      "news_sources": 1,
      "news_summary": "This is a clean next-7-day event window catalyst: the stock is in an uptrend but sitting near short-term support, so earnings can quickly resolve direction. ([businesswire.com][7])",
      "reason": "",
      "logic_pillars": {
        "technical": "F1: LatestPrice=118.13 (type=Close, asof=2026-02-19) is above F2 SMA200=92.18 and F4 EMA55=115.05, but slightly below F5 EMA21=118.66; F3 remains UPTREND.",
        "volume_analysis": "V1 RVOL20=0.55 is light, so pre-earnings positioning looks muted and leaves room for a sharp post-event volume expansion.",
        "news_catalyst": "N1 unavailable; see external_intel for the Feb 26 earnings event window."
      },
      "divergence": "No major rating divergence (F6 SA Overall=Buy is broadly aligned with F3 UPTREND), but the F5 micro-break plus low V1 means execution should wait for earnings reaction.",
      "action_plan": "Pre-earnings risk control: treat F5 EMA21=118.66 as immediate reclaim line and F4 EMA55=115.05 as deeper support. Avoid oversized positioning before the Feb 26 event.",
      "break_confirm_days": null,
      "trigger_count": 1.0,
      "primary_trigger_key": "EARNINGS_7D",
      "trigger_details": {
        "trigger_type": "Earnings 7D",
        "current_price": 118.12999725341797,
        "key_level": "N/A",
        "details": "Earnings in 6 days: 2026-02-26",
        "break_confirm_days": NaN,
        "trigger_count": "1",
        "primary_trigger_key": "EARNINGS_7D"
      },
      "sector": "Unknown",
      "quant_score": 4.15,
      "last_price": 118.12999725341797,
      "day_change_pct": null,
      "picked_date": "7/1/2025",
      "indicator_asof": "2026-02-19",
      "dte": 6,
      "next_earnings": "2026-02-26",
      "dist_sma200_pct": 28.153385742525593,
      "dist_ema21_pct": -0.4448661798135257,
      "dist_ema55_pct": 2.6792968007026414,
      "sma200": 92.17860033035278,
      "ema55": 115.0475323985756,
      "ema21": 118.65786596880163,
      "vol_ratio": 0.5474880170424286,
      "latest_price": 118.12999725341797,
      "price_type": "Close",
      "price_timestamp": "2026-02-19",
      "news_blurb": "Willdan will release Q4/FY2025 results after market close on February 26, 2026 (conference call at 5:30 p.m. ET). ([businesswire.com][7]) \u00b7 21d \u00b7 1 src"
    },
    {
      "ticker": "CDE",
      "verdict": "TREND_CONFIRMATION",
      "urgency": 75,
      "signal": "LOW",
      "news": "\ud83d\udfe9\ud83d\udfe9 +0.50",
      "news_sentiment_raw": 0.5,
      "volume_alert": false,
      "trend_color": "GREEN",
      "news_headline": "Coeur Mining reported Q4 and full-year 2025 results with record financial metrics and issued 2026 guidance. ([coeur.com][8])",
      "news_age": "2d",
      "news_sources": 1,
      "news_summary": "Company disclosures highlighted record quarterly/full-year results, strong cash generation, and 2026 guidance, which supports the broader precious-metals trend backdrop already reflected in the chart. ([coeur.com][8])",
      "reason": "",
      "logic_pillars": {
        "technical": "F1: LatestPrice=24.06 (type=Close, asof=2026-02-19) is above F2 SMA200=18.08, F4 EMA55=20.59, and F5 EMA21=22.16; F3 confirms UPTREND.",
        "volume_analysis": "V1 RVOL20=1.01 is neutral-to-average, which supports trend maintenance but does not indicate a fresh institutional acceleration.",
        "news_catalyst": "N1 unavailable; see external_intel for company-reported record results/guidance."
      },
      "divergence": "F6 SA Overall=Strong Buy is aligned with F3 UPTREND and supportive external_intel; the only limitation is average V1, which lowers urgency versus SSRM.",
      "action_plan": "Trend remains valid while above F5 EMA21=22.16. If momentum weakens, use F4 EMA55=20.59 as the next risk-control line rather than reacting to minor noise.",
      "break_confirm_days": null,
      "trigger_count": null,
      "primary_trigger_key": null,
      "trigger_details": {
        "trigger_type": "",
        "current_price": null,
        "key_level": "N/A",
        "details": "",
        "break_confirm_days": null,
        "trigger_count": null,
        "primary_trigger_key": null
      },
      "sector": "Unknown",
      "quant_score": 4.99,
      "last_price": 24.059999465942383,
      "day_change_pct": null,
      "picked_date": "9/15/2025",
      "indicator_asof": "2026-02-19",
      "dte": 75,
      "next_earnings": "2026-05-06",
      "dist_sma200_pct": 33.11027668781966,
      "dist_ema21_pct": 8.574734148691622,
      "dist_ema55_pct": 16.847829627027462,
      "sma200": 18.07523811431158,
      "ema55": 20.59088264004622,
      "ema21": 22.15985114270926,
      "vol_ratio": 1.0132826766127925,
      "latest_price": 24.059999465942383,
      "price_type": "Close",
      "price_timestamp": "2026-02-19",
      "news_blurb": "Coeur Mining reported Q4 and full-year 2025 results with record financial metrics and issued 2026 guidance. ([coeur.com][8]) \u00b7 2d \u00b7 1 src"
    }
  ],
  "table_view_model": [
    {
      "ticker": "AGX",
      "last_price": 432.17999267578125,
      "day_change_pct": null,
      "next_earnings": "2026-03-26",
      "quant_score": 3.3,
      "value_grade": "\u26ab F",
      "growth_grade": "\ud83d\udfe2 A-",
      "profitability_grade": "\ud83d\udfe2 A",
      "momentum_grade": "\ud83d\udfe2 A+",
      "eps_revisions_grade": "\ud83d\udfe2 A-",
      "hold_streak_days": 80,
      "ap_rule_action": "",
      "hold_countdown": 100.0,
      "dte": 34,
      "return_pct": 65.92124421807809,
      "company_name": "Industrials",
      "quant_rating": "Hold",
      "quant_rating_emoji": "\ud83d\udfe0 Hold",
      "sma200": 273.45803405761717,
      "ema55": 354.7520389090743,
      "ema21": 382.12984022754824,
      "rsi14": 67.38192191852619,
      "atr14_pct": 5.762352018377478,
      "vol_ratio": 0.6824897756554219,
      "ema21_fmt": "\ud83d\udfe2 $382.13",
      "ema55_fmt": "\ud83d\udfe2 $354.75",
      "sma200_fmt": "\ud83d\udfe2 $273.46",
      "vol_fmt": "0.7x",
      "rsi14_fmt": "67",
      "earnings_fmt": "2026-03-26",
      "Day%": NaN,
      "picked_date": "10/15/2024"
    },
    {
      "ticker": "ALL",
      "last_price": 203.22000122070312,
      "day_change_pct": null,
      "next_earnings": "2026-04-29",
      "quant_score": 3.41,
      "value_grade": "\ud83d\udfe1 B",
      "growth_grade": "\u26ab F",
      "profitability_grade": "\ud83d\udfe2 A",
      "momentum_grade": "\ud83d\udfe0 C-",
      "eps_revisions_grade": "\ud83d\udfe1 B+",
      "hold_streak_days": 15,
      "ap_rule_action": "",
      "hold_countdown": 165.0,
      "dte": 68,
      "return_pct": 1.0699535276671814,
      "company_name": "Financials",
      "quant_rating": "Hold",
      "quant_rating_emoji": "\ud83d\udfe0 Hold",
      "sma200": 201.72627082824707,
      "ema55": 203.69012064194516,
      "ema21": 204.3195161099995,
      "rsi14": 49.079151790612904,
      "atr14_pct": 2.778009699012018,
      "vol_ratio": 0.9813439513242663,
      "ema21_fmt": "\ud83d\udfe0 $204.32",
      "ema55_fmt": "\ud83d\udfe0 $203.69",
      "sma200_fmt": "\ud83d\udfe1 $201.73",
      "vol_fmt": "1.0x",
      "rsi14_fmt": "49",
      "earnings_fmt": "2026-04-29",
      "Day%": NaN,
      "picked_date": "1/2/2025"
    },
    {
      "ticker": "APP",
      "last_price": 412.0,
      "day_change_pct": null,
      "next_earnings": "2026-05-06",
      "quant_score": 3.26,
      "value_grade": "\ud83d\udfe0 C-",
      "growth_grade": "\ud83d\udfe2 A-",
      "profitability_grade": "\ud83d\udfe2 A+",
      "momentum_grade": "\ud83d\udfe0 C",
      "eps_revisions_grade": "\ud83d\udfe1 B+",
      "hold_streak_days": 8,
      "ap_rule_action": "",
      "hold_countdown": 172.0,
      "dte": 75,
      "return_pct": -1.0543079801119861,
      "company_name": "Information Technology",
      "quant_rating": "Hold",
      "quant_rating_emoji": "\ud83d\udfe0 Hold",
      "sma200": 505.67910034179687,
      "ema55": 535.1280388939507,
      "ema21": 462.01235832949624,
      "rsi14": 39.938319447440435,
      "atr14_pct": 9.589349888320418,
      "vol_ratio": 0.7595705001555155,
      "ema21_fmt": "\ud83d\udd34 $462.01",
      "ema55_fmt": "\ud83d\udd34 $535.13",
      "sma200_fmt": "\ud83d\udd34 $505.68",
      "vol_fmt": "0.8x",
      "rsi14_fmt": "40",
      "earnings_fmt": "2026-05-06",
      "Day%": NaN,
      "picked_date": "11/15/2023"
    },
    {
      "ticker": "ARQT",
      "last_price": 27.950000762939453,
      "day_change_pct": null,
      "next_earnings": "2026-02-25",
      "quant_score": 4.25,
      "value_grade": "\ud83d\udd34 D",
      "growth_grade": "\ud83d\udfe2 A-",
      "profitability_grade": "\ud83d\udfe1 B-",
      "momentum_grade": "\ud83d\udfe2 A-",
      "eps_revisions_grade": "\ud83d\udfe2 A",
      "hold_streak_days": 0,
      "ap_rule_action": "",
      "hold_countdown": NaN,
      "dte": 5,
      "return_pct": 12.972103994911155,
      "company_name": "Health Care",
      "quant_rating": "Buy",
      "quant_rating_emoji": "\ud83d\udfe1 Buy",
      "sma200": 20.383949971199037,
      "ema55": 26.654202571436272,
      "ema21": 26.733072725462005,
      "rsi14": 58.70831580880691,
      "atr14_pct": 4.0561172101125385,
      "vol_ratio": 1.05019866517776,
      "ema21_fmt": "\ud83d\udfe2 $26.73",
      "ema55_fmt": "\ud83d\udfe2 $26.65",
      "sma200_fmt": "\ud83d\udfe2 $20.38",
      "vol_fmt": "1.1x",
      "rsi14_fmt": "59",
      "earnings_fmt": "\u26a0\ufe0f 2026-02-25",
      "Day%": NaN,
      "picked_date": "3/17/2025"
    },
    {
      "ticker": "ATGE",
      "last_price": 96.75,
      "day_change_pct": null,
      "next_earnings": "2026-05-07",
      "quant_score": 3.31,
      "value_grade": "\ud83d\udfe0 C+",
      "growth_grade": "\ud83d\udfe0 C+",
      "profitability_grade": "\ud83d\udfe1 B+",
      "momentum_grade": "\ud83d\udd34 D+",
      "eps_revisions_grade": "\ud83d\udfe2 A+",
      "hold_streak_days": 9,
      "ap_rule_action": "",
      "hold_countdown": 171.0,
      "dte": 76,
      "return_pct": -11.83793808300936,
      "company_name": "Consumer Discretionary",
      "quant_rating": "Hold",
      "quant_rating_emoji": "\ud83d\udfe0 Hold",
      "sma200": 120.15875,
      "ema55": 106.43757746644495,
      "ema21": 102.37327590001287,
      "rsi14": 38.22647643452596,
      "atr14_pct": 4.55308743708735,
      "vol_ratio": 0.9031089872224451,
      "ema21_fmt": "\ud83d\udd34 $102.37",
      "ema55_fmt": "\ud83d\udd34 $106.44",
      "sma200_fmt": "\ud83d\udd34 $120.16",
      "vol_fmt": "0.9x",
      "rsi14_fmt": "38",
      "earnings_fmt": "2026-05-07",
      "Day%": NaN,
      "picked_date": "7/15/2024"
    },
    {
      "ticker": "B",
      "last_price": 48.54999923706055,
      "day_change_pct": null,
      "next_earnings": "2026-05-06",
      "quant_score": 4.96,
      "value_grade": "\ud83d\udfe1 B",
      "growth_grade": "\ud83d\udfe2 A-",
      "profitability_grade": "\ud83d\udfe2 A+",
      "momentum_grade": "\ud83d\udfe2 A-",
      "eps_revisions_grade": "\ud83d\udfe2 A-",
      "hold_streak_days": 0,
      "ap_rule_action": "",
      "hold_countdown": NaN,
      "dte": 75,
      "return_pct": 9.980416048785983,
      "company_name": "Materials",
      "quant_rating": "Strong Buy",
      "quant_rating_emoji": "\ud83d\udfe2 Strong Buy",
      "sma200": 45.406217856485334,
      "ema55": 45.685208627222075,
      "ema21": 47.512033939707685,
      "rsi14": 53.690144328598706,
      "atr14_pct": 4.605264415541724,
      "vol_ratio": 0.6460637714031447,
      "ema21_fmt": "\ud83d\udfe1 $47.51",
      "ema55_fmt": "\ud83d\udfe2 $45.69",
      "sma200_fmt": "\ud83d\udfe2 $45.41",
      "vol_fmt": "0.6x",
      "rsi14_fmt": "54",
      "earnings_fmt": "2026-05-06",
      "Day%": NaN,
      "picked_date": "1/2/2026"
    },
    {
      "ticker": "BLBD",
      "last_price": 60.52000045776367,
      "day_change_pct": null,
      "next_earnings": "2026-05-06",
      "quant_score": 3.94,
      "value_grade": "\ud83d\udfe1 B",
      "growth_grade": "\ud83d\udfe0 C",
      "profitability_grade": "\ud83d\udfe2 A-",
      "momentum_grade": "\ud83d\udfe1 B+",
      "eps_revisions_grade": "\ud83d\udfe1 B+",
      "hold_streak_days": 0,
      "ap_rule_action": "",
      "hold_countdown": NaN,
      "dte": 75,
      "return_pct": 14.56,
      "company_name": "Industrials",
      "quant_rating": "Buy",
      "quant_rating_emoji": "\ud83d\udfe1 Buy",
      "sma200": 49.86712509155274,
      "ema55": 52.82069104534513,
      "ema21": 55.22831025118665,
      "rsi14": 67.35754925227202,
      "atr14_pct": 3.8763953627017242,
      "vol_ratio": 1.0889329066991722,
      "ema21_fmt": "\ud83d\udfe2 $55.23",
      "ema55_fmt": "\ud83d\udfe2 $52.82",
      "sma200_fmt": "\ud83d\udfe2 $49.87",
      "vol_fmt": "1.1x",
      "rsi14_fmt": "67",
      "earnings_fmt": "2026-05-06",
      "Day%": NaN,
      "picked_date": "5/15/2024"
    },
    {
      "ticker": "BRK.B",
      "last_price": 496.94000244140625,
      "day_change_pct": null,
      "next_earnings": "2026-02-28",
      "quant_score": 4.97,
      "value_grade": "\ud83d\udfe0 C",
      "growth_grade": "\ud83d\udfe1 B-",
      "profitability_grade": "\ud83d\udfe2 A+",
      "momentum_grade": "\ud83d\udfe0 C-",
      "eps_revisions_grade": "\ud83d\udfe1 B+",
      "hold_streak_days": 0,
      "ap_rule_action": "",
      "hold_countdown": NaN,
      "dte": 8,
      "return_pct": 21.77,
      "company_name": "Financials",
      "quant_rating": "Strong Buy",
      "quant_rating_emoji": "\ud83d\udfe2 Strong Buy",
      "sma200": 492.94014907836913,
      "ema55": 495.4104369384351,
      "ema21": 496.024648846751,
      "rsi14": 51.414573348594594,
      "atr14_pct": 1.487712950044977,
      "vol_ratio": 0.5226801588138154,
      "ema21_fmt": "\ud83d\udfe1 $496.02",
      "ema55_fmt": "\ud83d\udfe1 $495.41",
      "sma200_fmt": "\ud83d\udfe2 $492.94",
      "vol_fmt": "0.5x",
      "rsi14_fmt": "51",
      "earnings_fmt": "\ud83d\udcc5 2026-02-28",
      "Day%": NaN,
      "picked_date": "7/1/2024"
    },
    {
      "ticker": "CAAP",
      "last_price": 29.0,
      "day_change_pct": null,
      "next_earnings": "2026-03-18",
      "quant_score": 4.0,
      "value_grade": "\ud83d\udfe1 B+",
      "growth_grade": "\ud83d\udfe0 C-",
      "profitability_grade": "\ud83d\udfe2 A-",
      "momentum_grade": "\ud83d\udfe1 B+",
      "eps_revisions_grade": "\ud83d\udfe1 B+",
      "hold_streak_days": 0,
      "ap_rule_action": "",
      "hold_countdown": NaN,
      "dte": 26,
      "return_pct": 156.41,
      "company_name": "Industrials",
      "quant_rating": "Buy",
      "quant_rating_emoji": "\ud83d\udfe1 Buy",
      "sma200": 22.23034999847412,
      "ema55": 26.916636565420937,
      "ema21": 28.458266742693823,
      "rsi14": 56.35956354706433,
      "atr14_pct": 3.6547637971739246,
      "vol_ratio": 0.8044078835676693,
      "ema21_fmt": "\ud83d\udfe2 $28.46",
      "ema55_fmt": "\ud83d\udfe2 $26.92",
      "sma200_fmt": "\ud83d\udfe2 $22.23",
      "vol_fmt": "0.8x",
      "rsi14_fmt": "56",
      "earnings_fmt": "2026-03-18",
      "Day%": NaN,
      "picked_date": "5/1/2023"
    },
    {
      "ticker": "CCL",
      "last_price": 31.549999237060547,
      "day_change_pct": null,
      "next_earnings": "2026-03-19",
      "quant_score": 4.62,
      "value_grade": "\ud83d\udd34 D",
      "growth_grade": "\ud83d\udfe0 C+",
      "profitability_grade": "\ud83d\udfe2 A",
      "momentum_grade": "\ud83d\udfe2 A-",
      "eps_revisions_grade": "\ud83d\udfe2 A-",
      "hold_streak_days": 0,
      "ap_rule_action": "",
      "hold_countdown": NaN,
      "dte": 27,
      "return_pct": 4.017373048204358,
      "company_name": "Consumer Discretionary",
      "quant_rating": "Strong Buy",
      "quant_rating_emoji": "\ud83d\udfe2 Strong Buy",
      "sma200": 28.125858907699584,
      "ema55": 30.28664273977477,
      "ema21": 31.529754867574617,
      "rsi14": 51.61548027893136,
      "atr14_pct": 4.056016213744083,
      "vol_ratio": 1.0904507358828155,
      "ema21_fmt": "\ud83d\udfe1 $31.53",
      "ema55_fmt": "\ud83d\udfe2 $30.29",
      "sma200_fmt": "\ud83d\udfe2 $28.13",
      "vol_fmt": "1.1x",
      "rsi14_fmt": "52",
      "earnings_fmt": "2026-03-19",
      "Day%": NaN,
      "picked_date": "11/1/2024"
    },
    {
      "ticker": "CDE",
      "last_price": 24.059999465942383,
      "day_change_pct": null,
      "next_earnings": "2026-05-06",
      "quant_score": 4.99,
      "value_grade": "\ud83d\udfe0 C",
      "growth_grade": "\ud83d\udfe2 A+",
      "profitability_grade": "\ud83d\udfe2 A-",
      "momentum_grade": "\ud83d\udfe2 A+",
      "eps_revisions_grade": "\ud83d\udfe2 A",
      "hold_streak_days": 0,
      "ap_rule_action": "",
      "hold_countdown": NaN,
      "dte": 75,
      "return_pct": 41.48209201813401,
      "company_name": "Materials",
      "quant_rating": "Strong Buy",
      "quant_rating_emoji": "\ud83d\udfe2 Strong Buy",
      "sma200": 18.07523811431158,
      "ema55": 20.59088264004622,
      "ema21": 22.15985114270926,
      "rsi14": 58.12840281106397,
      "atr14_pct": 7.432833590919899,
      "vol_ratio": 1.0132826766127925,
      "ema21_fmt": "\ud83d\udfe2 $22.16",
      "ema55_fmt": "\ud83d\udfe2 $20.59",
      "sma200_fmt": "\ud83d\udfe2 $18.08",
      "vol_fmt": "1.0x",
      "rsi14_fmt": "58",
      "earnings_fmt": "2026-05-06",
      "Day%": NaN,
      "picked_date": "9/15/2025"
    },
    {
      "ticker": "CLS",
      "last_price": 291.3299865722656,
      "day_change_pct": null,
      "next_earnings": "2026-04-23",
      "quant_score": 4.81,
      "value_grade": "\ud83d\udfe0 C+",
      "growth_grade": "\ud83d\udfe2 A",
      "profitability_grade": "\ud83d\udfe1 B",
      "momentum_grade": "\ud83d\udfe2 A",
      "eps_revisions_grade": "\ud83d\udfe1 B+",
      "hold_streak_days": 0,
      "ap_rule_action": "",
      "hold_countdown": NaN,
      "dte": 62,
      "return_pct": 18.379681363486686,
      "company_name": "Information Technology",
      "quant_rating": "Strong Buy",
      "quant_rating_emoji": "\ud83d\udfe2 Strong Buy",
      "sma200": 234.30990005493163,
      "ema55": 299.13276337195924,
      "ema21": 296.35364358491853,
      "rsi14": 47.72960235325766,
      "atr14_pct": 7.5434285546605615,
      "vol_ratio": 0.5124907179693301,
      "ema21_fmt": "\ud83d\udfe0 $296.35",
      "ema55_fmt": "\ud83d\udfe0 $299.13",
      "sma200_fmt": "\ud83d\udfe2 $234.31",
      "vol_fmt": "0.5x",
      "rsi14_fmt": "48",
      "earnings_fmt": "2026-04-23",
      "Day%": NaN,
      "picked_date": "11/15/2024"
    },
    {
      "ticker": "CRDO",
      "last_price": 130.66000366210938,
      "day_change_pct": null,
      "next_earnings": "2026-03-02",
      "quant_score": 4.9,
      "value_grade": "\ud83d\udfe0 C",
      "growth_grade": "\ud83d\udfe2 A+",
      "profitability_grade": "\ud83d\udfe1 B",
      "momentum_grade": "\ud83d\udfe1 B+",
      "eps_revisions_grade": "\ud83d\udfe2 A+",
      "hold_streak_days": 0,
      "ap_rule_action": "",
      "hold_countdown": NaN,
      "dte": 10,
      "return_pct": 1.4874413387133985,
      "company_name": "Information Technology",
      "quant_rating": "Strong Buy",
      "quant_rating_emoji": "\ud83d\udfe2 Strong Buy",
      "sma200": 123.73447507858276,
      "ema55": 135.98195535221944,
      "ema21": 126.9478063016094,
      "rsi14": 51.19027127788825,
      "atr14_pct": 8.615030505914374,
      "vol_ratio": 0.46991747137509615,
      "ema21_fmt": "\ud83d\udfe1 $126.95",
      "ema55_fmt": "\ud83d\udfe0 $135.98",
      "sma200_fmt": "\ud83d\udfe2 $123.73",
      "vol_fmt": "0.5x",
      "rsi14_fmt": "51",
      "earnings_fmt": "\ud83d\udcc5 2026-03-02",
      "Day%": NaN,
      "picked_date": "2/3/2025"
    },
    {
      "ticker": "DY",
      "last_price": 426.135009765625,
      "day_change_pct": null,
      "next_earnings": "2026-03-04",
      "quant_score": 4.767100977198697,
      "value_grade": "\ud83d\udfe0 C-",
      "growth_grade": "\ud83d\udfe1 B+",
      "profitability_grade": "\ud83d\udfe1 B-",
      "momentum_grade": "\ud83d\udfe2 A",
      "eps_revisions_grade": "\ud83d\udfe2 A",
      "hold_streak_days": 0,
      "ap_rule_action": "",
      "hold_countdown": NaN,
      "dte": 12,
      "return_pct": 11.748111029662638,
      "company_name": "Industrials",
      "quant_rating": "Strong Buy",
      "quant_rating_emoji": "\ud83d\udfe2 Strong Buy",
      "sma200": 392.7410848866338,
      "ema55": 384.03578855359825,
      "ema21": 400.84473389561884,
      "rsi14": 63.80513309162848,
      "atr14_pct": 4.277709359374601,
      "vol_ratio": 0.3294509478346154,
      "ema21_fmt": "\ud83d\udfe2 $400.84",
      "ema55_fmt": "\ud83d\udfe2 $384.04",
      "sma200_fmt": "\ud83d\udfe2 $392.74",
      "vol_fmt": "0.3x",
      "rsi14_fmt": "64",
      "earnings_fmt": "\ud83d\udcc5 2026-03-04",
      "Day%": NaN,
      "picked_date": "2/2/2026"
    },
    {
      "ticker": "EAT",
      "last_price": 150.61000061035156,
      "day_change_pct": null,
      "next_earnings": "2026-04-29",
      "quant_score": 4.66,
      "value_grade": "\ud83d\udfe0 C",
      "growth_grade": "\ud83d\udfe2 A-",
      "profitability_grade": "\ud83d\udfe2 A",
      "momentum_grade": "\ud83d\udfe1 B",
      "eps_revisions_grade": "\ud83d\udfe2 A+",
      "hold_streak_days": 0,
      "ap_rule_action": "",
      "hold_countdown": NaN,
      "dte": 68,
      "return_pct": 7.1063857126664205,
      "company_name": "Consumer Discretionary",
      "quant_rating": "Strong Buy",
      "quant_rating_emoji": "\ud83d\udfe2 Strong Buy",
      "sma200": 150.2322499847412,
      "ema55": 154.37989574168793,
      "ema21": 160.43576002509243,
      "rsi14": 40.28062608048451,
      "atr14_pct": 4.849594129096019,
      "vol_ratio": 0.790062572157528,
      "ema21_fmt": "\ud83d\udd34 $160.44",
      "ema55_fmt": "\ud83d\udd34 $154.38",
      "sma200_fmt": "\ud83d\udfe1 $150.23",
      "vol_fmt": "0.8x",
      "rsi14_fmt": "40",
      "earnings_fmt": "2026-04-29",
      "Day%": NaN,
      "picked_date": "4/15/2025"
    },
    {
      "ticker": "EZPW",
      "last_price": 25.270000457763672,
      "day_change_pct": null,
      "next_earnings": "2026-04-29",
      "quant_score": 4.87,
      "value_grade": "\ud83d\udfe0 C+",
      "growth_grade": "\ud83d\udfe1 B+",
      "profitability_grade": "\ud83d\udfe0 C+",
      "momentum_grade": "\ud83d\udfe2 A+",
      "eps_revisions_grade": "\ud83d\udfe2 A-",
      "hold_streak_days": 0,
      "ap_rule_action": "",
      "hold_countdown": NaN,
      "dte": 68,
      "return_pct": 38.364624660165774,
      "company_name": "Financials",
      "quant_rating": "Strong Buy",
      "quant_rating_emoji": "\ud83d\udfe2 Strong Buy",
      "sma200": 17.405799989700316,
      "ema55": 21.701614874901363,
      "ema21": 23.430271405623,
      "rsi14": 70.43016174530935,
      "atr14_pct": 3.4050487532495186,
      "vol_ratio": 0.6684901024523666,
      "ema21_fmt": "\ud83d\udfe2 $23.43",
      "ema55_fmt": "\ud83d\udfe2 $21.70",
      "sma200_fmt": "\ud83d\udfe2 $17.41",
      "vol_fmt": "0.7x",
      "rsi14_fmt": "\ud83d\udd34 70",
      "earnings_fmt": "2026-04-29",
      "Day%": NaN,
      "picked_date": "4/1/2025"
    },
    {
      "ticker": "GM",
      "last_price": 81.6050033569336,
      "day_change_pct": null,
      "next_earnings": "2026-04-28",
      "quant_score": 4.937888198757764,
      "value_grade": "\ud83d\udfe1 B-",
      "growth_grade": "\ud83d\udfe1 B-",
      "profitability_grade": "\ud83d\udfe2 A+",
      "momentum_grade": "\ud83d\udfe2 A",
      "eps_revisions_grade": "\ud83d\udfe1 B+",
      "hold_streak_days": 0,
      "ap_rule_action": "",
      "hold_countdown": NaN,
      "dte": 67,
      "return_pct": 0.3143967744748808,
      "company_name": "Consumer Discretionary",
      "quant_rating": "Strong Buy",
      "quant_rating_emoji": "\ud83d\udfe2 Strong Buy",
      "sma200": 82.35152169932489,
      "ema55": 80.36004834696028,
      "ema21": 81.666562252686,
      "rsi14": 50.662453962342816,
      "atr14_pct": 3.0219913760411963,
      "vol_ratio": 0.5264770075003856,
      "ema21_fmt": "\ud83d\udfe0 $81.67",
      "ema55_fmt": "\ud83d\udfe2 $80.36",
      "sma200_fmt": "\ud83d\udfe0 $82.35",
      "vol_fmt": "0.5x",
      "rsi14_fmt": "51",
      "earnings_fmt": "2026-04-28",
      "Day%": NaN,
      "picked_date": "2/17/2026"
    },
    {
      "ticker": "INCY",
      "last_price": 101.7300033569336,
      "day_change_pct": null,
      "next_earnings": "2026-04-28",
      "quant_score": 3.27,
      "value_grade": "\ud83d\udfe2 A",
      "growth_grade": "\ud83d\udfe2 A+",
      "profitability_grade": "\ud83d\udfe2 A+",
      "momentum_grade": "\ud83d\udfe1 B",
      "eps_revisions_grade": "\ud83d\udd34 D+",
      "hold_streak_days": 9,
      "ap_rule_action": "",
      "hold_countdown": 171.0,
      "dte": 67,
      "return_pct": -3.561481703478263,
      "company_name": "Health Care",
      "quant_rating": "Hold",
      "quant_rating_emoji": "\ud83d\udfe0 Hold",
      "sma200": 95.80706351143974,
      "ema55": 101.44701471263458,
      "ema21": 102.43025070929038,
      "rsi14": 48.5317489907844,
      "atr14_pct": 3.6583349084883747,
      "vol_ratio": 0.7611279057646201,
      "ema21_fmt": "\ud83d\udfe0 $102.43",
      "ema55_fmt": "\ud83d\udfe1 $101.45",
      "sma200_fmt": "\ud83d\udfe2 $95.81",
      "vol_fmt": "0.8x",
      "rsi14_fmt": "49",
      "earnings_fmt": "2026-04-28",
      "Day%": NaN,
      "picked_date": "11/3/2025"
    },
    {
      "ticker": "KGC",
      "last_price": 33.45000076293945,
      "day_change_pct": null,
      "next_earnings": "2026-05-12",
      "quant_score": 4.83,
      "value_grade": "\ud83d\udd34 D",
      "growth_grade": "\ud83d\udfe2 A-",
      "profitability_grade": "\ud83d\udfe2 A+",
      "momentum_grade": "\ud83d\udfe2 A-",
      "eps_revisions_grade": "\ud83d\udfe1 B+",
      "hold_streak_days": 0,
      "ap_rule_action": "",
      "hold_countdown": NaN,
      "dte": 81,
      "return_pct": 49.82526181528069,
      "company_name": "Materials",
      "quant_rating": "Strong Buy",
      "quant_rating_emoji": "\ud83d\udfe2 Strong Buy",
      "sma200": 27.093888933696444,
      "ema55": 31.553373446969893,
      "ema21": 33.59206040426475,
      "rsi14": 50.49004085338374,
      "atr14_pct": 5.413573548605339,
      "vol_ratio": 1.09969092033017,
      "ema21_fmt": "\ud83d\udfe0 $33.59",
      "ema55_fmt": "\ud83d\udfe2 $31.55",
      "sma200_fmt": "\ud83d\udfe2 $27.09",
      "vol_fmt": "1.1x",
      "rsi14_fmt": "50",
      "earnings_fmt": "2026-05-12",
      "Day%": NaN,
      "picked_date": "9/2/2025"
    },
    {
      "ticker": "MFC",
      "last_price": 36.16999816894531,
      "day_change_pct": null,
      "next_earnings": "2026-05-06",
      "quant_score": 4.71,
      "value_grade": "\ud83d\udfe1 B+",
      "growth_grade": "\ud83d\udfe0 C-",
      "profitability_grade": "\ud83d\udfe2 A+",
      "momentum_grade": "\ud83d\udfe1 B",
      "eps_revisions_grade": "\ud83d\udfe1 B-",
      "hold_streak_days": 0,
      "ap_rule_action": "",
      "hold_countdown": NaN,
      "dte": 75,
      "return_pct": 16.49856485145074,
      "company_name": "Financials",
      "quant_rating": "Strong Buy",
      "quant_rating_emoji": "\ud83d\udfe2 Strong Buy",
      "sma200": 33.021634063720704,
      "ema55": 36.47886105076057,
      "ema21": 37.20098481598897,
      "rsi14": 42.53947567002198,
      "atr14_pct": 2.2325324619101035,
      "vol_ratio": 0.6082953922135019,
      "ema21_fmt": "\ud83d\udd34 $37.20",
      "ema55_fmt": "\ud83d\udfe0 $36.48",
      "sma200_fmt": "\ud83d\udfe2 $33.02",
      "vol_fmt": "0.6x",
      "rsi14_fmt": "43",
      "earnings_fmt": "2026-05-06",
      "Day%": NaN,
      "picked_date": "5/1/2025"
    },
    {
      "ticker": "MU",
      "last_price": 417.3500061035156,
      "day_change_pct": null,
      "next_earnings": "2026-03-18",
      "quant_score": 5.0,
      "value_grade": "\ud83d\udfe0 C+",
      "growth_grade": "\ud83d\udfe2 A+",
      "profitability_grade": "\ud83d\udfe2 A+",
      "momentum_grade": "\ud83d\udfe2 A+",
      "eps_revisions_grade": "\ud83d\udfe2 A",
      "hold_streak_days": 0,
      "ap_rule_action": "",
      "hold_countdown": NaN,
      "dte": 26,
      "return_pct": 103.46743627622392,
      "company_name": "Information Technology",
      "quant_rating": "Strong Buy",
      "quant_rating_emoji": "\ud83d\udfe2 Strong Buy",
      "sma200": 248.82037389846076,
      "ema55": 343.4380869922463,
      "ema21": 394.1138896014279,
      "rsi14": 59.41931018784558,
      "atr14_pct": 6.08244690064412,
      "vol_ratio": 0.5612691001863521,
      "ema21_fmt": "\ud83d\udfe2 $394.11",
      "ema55_fmt": "\ud83d\udfe2 $343.44",
      "sma200_fmt": "\ud83d\udfe2 $248.82",
      "vol_fmt": "0.6x",
      "rsi14_fmt": "59",
      "earnings_fmt": "2026-03-18",
      "Day%": NaN,
      "picked_date": "10/15/2025"
    },
    {
      "ticker": "NEM",
      "last_price": 125.4000015258789,
      "day_change_pct": null,
      "next_earnings": "2026-04-22",
      "quant_score": 4.95,
      "value_grade": "\ud83d\udd34 D+",
      "growth_grade": "\ud83d\udfe2 A-",
      "profitability_grade": "\ud83d\udfe2 A+",
      "momentum_grade": "\ud83d\udfe2 A-",
      "eps_revisions_grade": "\ud83d\udfe2 A-",
      "hold_streak_days": 0,
      "ap_rule_action": "",
      "hold_countdown": NaN,
      "dte": 61,
      "return_pct": 9.808078009162845,
      "company_name": "Materials",
      "quant_rating": "Strong Buy",
      "quant_rating_emoji": "\ud83d\udfe2 Strong Buy",
      "sma200": 107.14409287249455,
      "ema55": 110.55383068556534,
      "ema21": 119.52707948769674,
      "rsi14": 58.09310658446644,
      "atr14_pct": 4.586378511456699,
      "vol_ratio": 0.7339815174563977,
      "ema21_fmt": "\ud83d\udfe2 $119.53",
      "ema55_fmt": "\ud83d\udfe2 $110.55",
      "sma200_fmt": "\ud83d\udfe2 $107.14",
      "vol_fmt": "0.7x",
      "rsi14_fmt": "58",
      "earnings_fmt": "2026-04-22",
      "Day%": NaN,
      "picked_date": "1/15/2026"
    },
    {
      "ticker": "OKTA",
      "last_price": 81.80000305175781,
      "day_change_pct": null,
      "next_earnings": "2026-03-04",
      "quant_score": 4.38,
      "value_grade": "\ud83d\udfe0 C-",
      "growth_grade": "\ud83d\udfe1 B",
      "profitability_grade": "\ud83d\udfe2 A",
      "momentum_grade": "\ud83d\udfe0 C+",
      "eps_revisions_grade": "\ud83d\udfe1 B+",
      "hold_streak_days": 0,
      "ap_rule_action": "",
      "hold_countdown": NaN,
      "dte": 12,
      "return_pct": -13.809629802555893,
      "company_name": "Information Technology",
      "quant_rating": "Buy",
      "quant_rating_emoji": "\ud83d\udfe1 Buy",
      "sma200": 93.81139999389649,
      "ema55": 87.47690499247136,
      "ema21": 86.20721599889092,
      "rsi14": 40.42789607762107,
      "atr14_pct": 4.598960253908457,
      "vol_ratio": 0.8540238107700987,
      "ema21_fmt": "\ud83d\udd34 $86.21",
      "ema55_fmt": "\ud83d\udd34 $87.48",
      "sma200_fmt": "\ud83d\udd34 $93.81",
      "vol_fmt": "0.9x",
      "rsi14_fmt": "40",
      "earnings_fmt": "\ud83d\udcc5 2026-03-04",
      "Day%": NaN,
      "picked_date": "2/15/2024"
    },
    {
      "ticker": "PARR",
      "last_price": 42.310001373291016,
      "day_change_pct": null,
      "next_earnings": "2026-02-24",
      "quant_score": 3.81,
      "value_grade": "\ud83d\udfe1 B",
      "growth_grade": "\ud83d\udfe2 A",
      "profitability_grade": "\ud83d\udfe0 C",
      "momentum_grade": "\ud83d\udfe2 A",
      "eps_revisions_grade": "\ud83d\udfe0 C-",
      "hold_streak_days": 0,
      "ap_rule_action": "",
      "hold_countdown": NaN,
      "dte": 4,
      "return_pct": 4.006455305819489,
      "company_name": "Energy",
      "quant_rating": "Buy",
      "quant_rating_emoji": "\ud83d\udfe1 Buy",
      "sma200": 38.22896822672042,
      "ema55": 39.34900973861328,
      "ema21": 40.4434587740516,
      "rsi14": 61.48386213800995,
      "atr14_pct": 4.323135642831272,
      "vol_ratio": 0.8600289525274701,
      "ema21_fmt": "\ud83d\udfe2 $40.44",
      "ema55_fmt": "\ud83d\udfe2 $39.35",
      "sma200_fmt": "\ud83d\udfe2 $38.23",
      "vol_fmt": "0.9x",
      "rsi14_fmt": "61",
      "earnings_fmt": "\u26a0\ufe0f 2026-02-24",
      "Day%": NaN,
      "picked_date": "11/17/2025"
    },
    {
      "ticker": "POWL",
      "last_price": 536.3599853515625,
      "day_change_pct": null,
      "next_earnings": "2026-05-05",
      "quant_score": 3.48,
      "value_grade": "\u26ab F",
      "growth_grade": "\ud83d\udfe0 C-",
      "profitability_grade": "\ud83d\udfe1 B+",
      "momentum_grade": "\ud83d\udfe2 A+",
      "eps_revisions_grade": "\ud83d\udfe2 A+",
      "hold_streak_days": 162,
      "ap_rule_action": "",
      "hold_countdown": 18.0,
      "dte": 74,
      "return_pct": 156.8486438831018,
      "company_name": "Industrials",
      "quant_rating": "Hold",
      "quant_rating_emoji": "\ud83d\udfe0 Hold",
      "sma200": 300.51029289245605,
      "ema55": 437.47580083936884,
      "ema21": 510.4131448216329,
      "rsi14": 61.4002885910348,
      "atr14_pct": 5.874967882784646,
      "vol_ratio": 0.6746726208436425,
      "ema21_fmt": "\ud83d\udfe2 $510.41",
      "ema55_fmt": "\ud83d\udfe2 $437.48",
      "sma200_fmt": "\ud83d\udfe2 $300.51",
      "vol_fmt": "0.7x",
      "rsi14_fmt": "61",
      "earnings_fmt": "2026-05-05",
      "Day%": NaN,
      "picked_date": "10/1/2024"
    },
    {
      "ticker": "PPC",
      "last_price": 42.45000076293945,
      "day_change_pct": null,
      "next_earnings": "2026-04-29",
      "quant_score": 2.88,
      "value_grade": "\ud83d\udfe1 B+",
      "growth_grade": "\u26ab F",
      "profitability_grade": "\ud83d\udfe1 B",
      "momentum_grade": "\ud83d\udfe0 C+",
      "eps_revisions_grade": "\ud83d\udfe0 C",
      "hold_streak_days": 141,
      "ap_rule_action": "",
      "hold_countdown": 39.0,
      "dte": 68,
      "return_pct": -1.1006776504808482,
      "company_name": "Consumer Staples",
      "quant_rating": "Hold",
      "quant_rating_emoji": "\ud83d\udfe0 Hold",
      "sma200": 42.14373888015747,
      "ema55": 41.385948779531844,
      "ema21": 42.63602517592374,
      "rsi14": 50.69999917303126,
      "atr14_pct": 2.9034429776965216,
      "vol_ratio": 0.965192007813048,
      "ema21_fmt": "\ud83d\udfe0 $42.64",
      "ema55_fmt": "\ud83d\udfe2 $41.39",
      "sma200_fmt": "\ud83d\udfe1 $42.14",
      "vol_fmt": "1.0x",
      "rsi14_fmt": "51",
      "earnings_fmt": "2026-04-29",
      "Day%": NaN,
      "picked_date": "9/16/2024"
    },
    {
      "ticker": "RCL",
      "last_price": 310.3500061035156,
      "day_change_pct": null,
      "next_earnings": "2026-04-28",
      "quant_score": 3.34,
      "value_grade": "\ud83d\udd34 D-",
      "growth_grade": "\ud83d\udfe2 A+",
      "profitability_grade": "\ud83d\udfe2 A",
      "momentum_grade": "\ud83d\udfe1 B+",
      "eps_revisions_grade": "\ud83d\udfe2 A-",
      "hold_streak_days": 79,
      "ap_rule_action": "",
      "hold_countdown": 101.0,
      "dte": 67,
      "return_pct": 141.05,
      "company_name": "Consumer Discretionary",
      "quant_rating": "Hold",
      "quant_rating_emoji": "\ud83d\udfe0 Hold",
      "sma200": 297.46648239135743,
      "ema55": 303.9819203492306,
      "ema21": 318.5581648266049,
      "rsi14": 47.80659341431705,
      "atr14_pct": 4.482318458040522,
      "vol_ratio": 0.6937956017963719,
      "ema21_fmt": "\ud83d\udd34 $318.56",
      "ema55_fmt": "\ud83d\udfe1 $303.98",
      "sma200_fmt": "\ud83d\udfe2 $297.47",
      "vol_fmt": "0.7x",
      "rsi14_fmt": "48",
      "earnings_fmt": "2026-04-28",
      "Day%": NaN,
      "picked_date": "3/15/2024"
    },
    {
      "ticker": "SKYW",
      "last_price": 101.94999694824219,
      "day_change_pct": null,
      "next_earnings": "2026-04-23",
      "quant_score": 3.39,
      "value_grade": "\ud83d\udfe2 A",
      "growth_grade": "\ud83d\udfe0 C-",
      "profitability_grade": "\ud83d\udfe1 B-",
      "momentum_grade": "\ud83d\udfe0 C-",
      "eps_revisions_grade": "\ud83d\udfe2 A+",
      "hold_streak_days": 40,
      "ap_rule_action": "",
      "hold_countdown": 140.0,
      "dte": 62,
      "return_pct": -2.7008204489033583,
      "company_name": "Industrials",
      "quant_rating": "Hold",
      "quant_rating_emoji": "\ud83d\udfe0 Hold",
      "sma200": 104.04284980773926,
      "ema55": 101.98505020074715,
      "ema21": 102.99460210944495,
      "rsi14": 48.63032614573696,
      "atr14_pct": 3.6619902294460225,
      "vol_ratio": 0.6957555415705196,
      "ema21_fmt": "\ud83d\udfe0 $102.99",
      "ema55_fmt": "\ud83d\udfe0 $101.99",
      "sma200_fmt": "\ud83d\udd34 $104.04",
      "vol_fmt": "0.7x",
      "rsi14_fmt": "49",
      "earnings_fmt": "2026-04-23",
      "Day%": NaN,
      "picked_date": "6/3/2024"
    },
    {
      "ticker": "SSRM",
      "last_price": 29.110000610351562,
      "day_change_pct": null,
      "next_earnings": "2026-05-05",
      "quant_score": 4.99,
      "value_grade": "\ud83d\udfe2 A",
      "growth_grade": "\ud83d\udfe2 A+",
      "profitability_grade": "\ud83d\udfe2 A-",
      "momentum_grade": "\ud83d\udfe2 A-",
      "eps_revisions_grade": "\ud83d\udfe2 A+",
      "hold_streak_days": 0,
      "ap_rule_action": "",
      "hold_countdown": NaN,
      "dte": 74,
      "return_pct": 35.5256848361046,
      "company_name": "Materials",
      "quant_rating": "Strong Buy",
      "quant_rating_emoji": "\ud83d\udfe2 Strong Buy",
      "sma200": 18.932350006103515,
      "ema55": 24.17760968552272,
      "ema21": 25.726814386635795,
      "rsi14": 61.29256664035779,
      "atr14_pct": 6.590122757605369,
      "vol_ratio": 1.3444847294844033,
      "ema21_fmt": "\ud83d\udfe2 $25.73",
      "ema55_fmt": "\ud83d\udfe2 $24.18",
      "sma200_fmt": "\ud83d\udfe2 $18.93",
      "vol_fmt": "1.3x",
      "rsi14_fmt": "61",
      "earnings_fmt": "2026-05-05",
      "Day%": NaN,
      "picked_date": "6/16/2025"
    },
    {
      "ticker": "STRL",
      "last_price": 415.1300048828125,
      "day_change_pct": null,
      "next_earnings": "2026-02-25",
      "quant_score": 4.05,
      "value_grade": "\ud83d\udd34 D+",
      "growth_grade": "\ud83d\udfe2 A-",
      "profitability_grade": "\ud83d\udfe1 B",
      "momentum_grade": "\ud83d\udfe2 A+",
      "eps_revisions_grade": "\ud83d\udfe0 C",
      "hold_streak_days": 0,
      "ap_rule_action": "",
      "hold_countdown": NaN,
      "dte": 5,
      "return_pct": 32.68871444119171,
      "company_name": "Industrials",
      "quant_rating": "Buy",
      "quant_rating_emoji": "\ud83d\udfe1 Buy",
      "sma200": 299.9353995513916,
      "ema55": 363.0553373575654,
      "ema21": 392.27403549773953,
      "rsi14": 60.57718002002849,
      "atr14_pct": 5.782316220593662,
      "vol_ratio": 1.1755179303817436,
      "ema21_fmt": "\ud83d\udfe2 $392.27",
      "ema55_fmt": "\ud83d\udfe2 $363.06",
      "sma200_fmt": "\ud83d\udfe2 $299.94",
      "vol_fmt": "1.2x",
      "rsi14_fmt": "61",
      "earnings_fmt": "\u26a0\ufe0f 2026-02-25",
      "Day%": NaN,
      "picked_date": "8/1/2025"
    },
    {
      "ticker": "SYF",
      "last_price": 72.26000213623047,
      "day_change_pct": null,
      "next_earnings": "2026-04-21",
      "quant_score": 3.09,
      "value_grade": "\ud83d\udfe0 C+",
      "growth_grade": "\ud83d\udfe0 C-",
      "profitability_grade": "\ud83d\udfe2 A+",
      "momentum_grade": "\ud83d\udfe0 C",
      "eps_revisions_grade": "\ud83d\udd34 D+",
      "hold_streak_days": 31,
      "ap_rule_action": "",
      "hold_countdown": 149.0,
      "dte": 60,
      "return_pct": -2.7740385291276937,
      "company_name": "Financials",
      "quant_rating": "Hold",
      "quant_rating_emoji": "\ud83d\udfe0 Hold",
      "sma200": 71.49813362121581,
      "ema55": 76.40402896787278,
      "ema21": 74.31871559709562,
      "rsi14": 39.99342112206965,
      "atr14_pct": 3.137605744574671,
      "vol_ratio": 0.7088306438366349,
      "ema21_fmt": "\ud83d\udd34 $74.32",
      "ema55_fmt": "\ud83d\udd34 $76.40",
      "sma200_fmt": "\ud83d\udfe1 $71.50",
      "vol_fmt": "0.7x",
      "rsi14_fmt": "40",
      "earnings_fmt": "2026-04-21",
      "Day%": NaN,
      "picked_date": "9/3/2024"
    },
    {
      "ticker": "TIGO",
      "last_price": 63.95000076293945,
      "day_change_pct": null,
      "next_earnings": "2026-02-26",
      "quant_score": 4.67,
      "value_grade": "\ud83d\udfe1 B",
      "growth_grade": "\ud83d\udfe2 A-",
      "profitability_grade": "\ud83d\udfe2 A",
      "momentum_grade": "\ud83d\udfe2 A+",
      "eps_revisions_grade": "\ud83d\udfe2 A-",
      "hold_streak_days": 0,
      "ap_rule_action": "",
      "hold_countdown": NaN,
      "dte": 6,
      "return_pct": 14.223713083574129,
      "company_name": "Communication Services",
      "quant_rating": "Strong Buy",
      "quant_rating_emoji": "\ud83d\udfe2 Strong Buy",
      "sma200": 56.386965204457766,
      "ema55": 58.645223611510325,
      "ema21": 62.91529217972773,
      "rsi14": 57.05950183135276,
      "atr14_pct": 3.2231344376269138,
      "vol_ratio": 1.1546142614999917,
      "ema21_fmt": "\ud83d\udfe2 $62.92",
      "ema55_fmt": "\ud83d\udfe2 $58.65",
      "sma200_fmt": "\ud83d\udfe2 $56.39",
      "vol_fmt": "1.2x",
      "rsi14_fmt": "57",
      "earnings_fmt": "\u26a0\ufe0f 2026-02-26",
      "Day%": NaN,
      "picked_date": "12/15/2025"
    },
    {
      "ticker": "TMUS",
      "last_price": 215.3000030517578,
      "day_change_pct": null,
      "next_earnings": "2026-04-23",
      "quant_score": 3.11,
      "value_grade": "\ud83d\udd34 D",
      "growth_grade": "\ud83d\udfe0 C+",
      "profitability_grade": "\ud83d\udfe2 A+",
      "momentum_grade": "\ud83d\udfe0 C",
      "eps_revisions_grade": "\ud83d\udd34 D-",
      "hold_streak_days": 12,
      "ap_rule_action": "",
      "hold_countdown": 168.0,
      "dte": 62,
      "return_pct": 49.55,
      "company_name": "Communication Services",
      "quant_rating": "Hold",
      "quant_rating_emoji": "\ud83d\udfe0 Hold",
      "sma200": 223.07300537109376,
      "ema55": 202.6390701631347,
      "ema21": 204.00989160875355,
      "rsi14": 65.3014674693942,
      "atr14_pct": 2.816582904145283,
      "vol_ratio": 0.6500490242719069,
      "ema21_fmt": "\ud83d\udfe2 $204.01",
      "ema55_fmt": "\ud83d\udfe2 $202.64",
      "sma200_fmt": "\ud83d\udd34 $223.07",
      "vol_fmt": "0.7x",
      "rsi14_fmt": "65",
      "earnings_fmt": "2026-04-23",
      "Day%": NaN,
      "picked_date": "9/15/2023"
    },
    {
      "ticker": "TTMI",
      "last_price": 100.38999938964844,
      "day_change_pct": null,
      "next_earnings": "2026-04-29",
      "quant_score": 4.97,
      "value_grade": "\ud83d\udfe0 C-",
      "growth_grade": "\ud83d\udfe2 A-",
      "profitability_grade": "\ud83d\udfe0 C-",
      "momentum_grade": "\ud83d\udfe2 A+",
      "eps_revisions_grade": "\ud83d\udfe2 A-",
      "hold_streak_days": 0,
      "ap_rule_action": "",
      "hold_countdown": NaN,
      "dte": 68,
      "return_pct": 47.93181825497871,
      "company_name": "Information Technology",
      "quant_rating": "Strong Buy",
      "quant_rating_emoji": "\ud83d\udfe2 Strong Buy",
      "sma200": 68.31833315652514,
      "ema55": 85.07116602817679,
      "ema21": 93.74931714885489,
      "rsi14": 60.000087927698544,
      "atr14_pct": 7.145141527667071,
      "vol_ratio": 0.6123874757708727,
      "ema21_fmt": "\ud83d\udfe2 $93.75",
      "ema55_fmt": "\ud83d\udfe2 $85.07",
      "sma200_fmt": "\ud83d\udfe2 $68.32",
      "vol_fmt": "0.6x",
      "rsi14_fmt": "60",
      "earnings_fmt": "2026-04-29",
      "Day%": NaN,
      "picked_date": "10/1/2025"
    },
    {
      "ticker": "TWLO",
      "last_price": 110.95999908447266,
      "day_change_pct": null,
      "next_earnings": "2026-04-30",
      "quant_score": 2.94,
      "value_grade": "\ud83d\udfe1 B-",
      "growth_grade": "\ud83d\udfe1 B",
      "profitability_grade": "\ud83d\udfe1 B",
      "momentum_grade": "\ud83d\udfe0 C+",
      "eps_revisions_grade": "\ud83d\udfe1 B-",
      "hold_streak_days": 12,
      "ap_rule_action": "",
      "hold_countdown": 168.0,
      "dte": 69,
      "return_pct": -14.960438495901181,
      "company_name": "Information Technology",
      "quant_rating": "Hold",
      "quant_rating_emoji": "\ud83d\udfe0 Hold",
      "sma200": 118.53725036621094,
      "ema55": 122.55637305171683,
      "ema21": 117.15580798232044,
      "rsi14": 40.3000832594365,
      "atr14_pct": 5.999663535590288,
      "vol_ratio": 0.5173131168505363,
      "ema21_fmt": "\ud83d\udd34 $117.16",
      "ema55_fmt": "\ud83d\udd34 $122.56",
      "sma200_fmt": "\ud83d\udd34 $118.54",
      "vol_fmt": "0.5x",
      "rsi14_fmt": "40",
      "earnings_fmt": "2026-04-30",
      "Day%": NaN,
      "picked_date": "2/1/2024"
    },
    {
      "ticker": "UBER",
      "last_price": 72.94000244140625,
      "day_change_pct": null,
      "next_earnings": "2026-05-06",
      "quant_score": 3.07,
      "value_grade": "\ud83d\udfe0 C+",
      "growth_grade": "\ud83d\udfe1 B",
      "profitability_grade": "\ud83d\udfe2 A+",
      "momentum_grade": "\ud83d\udd34 D-",
      "eps_revisions_grade": "\ud83d\udd34 D+",
      "hold_streak_days": 39,
      "ap_rule_action": "",
      "hold_countdown": 141.0,
      "dte": 75,
      "return_pct": -13.37018396053267,
      "company_name": "Industrials",
      "quant_rating": "Hold",
      "quant_rating_emoji": "\ud83d\udfe0 Hold",
      "sma200": 88.87845027923584,
      "ema55": 80.78430834638112,
      "ema21": 75.84816238762909,
      "rsi14": 37.11011230525708,
      "atr14_pct": 3.6369078658909237,
      "vol_ratio": 0.649452640237177,
      "ema21_fmt": "\ud83d\udd34 $75.85",
      "ema55_fmt": "\ud83d\udd34 $80.78",
      "sma200_fmt": "\ud83d\udd34 $88.88",
      "vol_fmt": "0.6x",
      "rsi14_fmt": "37",
      "earnings_fmt": "2026-05-06",
      "Day%": NaN,
      "picked_date": "6/1/2023"
    },
    {
      "ticker": "UNFI",
      "last_price": 38.68000030517578,
      "day_change_pct": null,
      "next_earnings": "2026-03-10",
      "quant_score": 4.82,
      "value_grade": "\ud83d\udfe2 A+",
      "growth_grade": "\ud83d\udfe2 A+",
      "profitability_grade": "\ud83d\udd34 D+",
      "momentum_grade": "\ud83d\udfe1 B+",
      "eps_revisions_grade": "\ud83d\udfe2 A",
      "hold_streak_days": 0,
      "ap_rule_action": "",
      "hold_countdown": NaN,
      "dte": 18,
      "return_pct": 18.121069674091927,
      "company_name": "Consumer Staples",
      "quant_rating": "Strong Buy",
      "quant_rating_emoji": "\ud83d\udfe2 Strong Buy",
      "sma200": 31.877949934005738,
      "ema55": 36.6794660522545,
      "ema21": 38.353224808960974,
      "rsi14": 53.72289537556588,
      "atr14_pct": 3.772638259939832,
      "vol_ratio": 0.6376463263666177,
      "ema21_fmt": "\ud83d\udfe1 $38.35",
      "ema55_fmt": "\ud83d\udfe2 $36.68",
      "sma200_fmt": "\ud83d\udfe2 $31.88",
      "vol_fmt": "0.6x",
      "rsi14_fmt": "54",
      "earnings_fmt": "\ud83d\udcc5 2026-03-10",
      "Day%": NaN,
      "picked_date": "5/15/2025"
    },
    {
      "ticker": "VISN",
      "last_price": 18.540000915527344,
      "day_change_pct": null,
      "next_earnings": "2026-02-26",
      "quant_score": 3.33,
      "value_grade": "\ud83d\udfe1 B+",
      "growth_grade": "\ud83d\udfe0 C-",
      "profitability_grade": "\ud83d\udfe2 A",
      "momentum_grade": "\ud83d\udfe2 A+",
      "eps_revisions_grade": "\ud83d\udd34 D+",
      "hold_streak_days": 2,
      "ap_rule_action": "",
      "hold_countdown": 178.0,
      "dte": 6,
      "return_pct": 9.26110270888695,
      "company_name": "Information Technology",
      "quant_rating": "Hold",
      "quant_rating_emoji": "\ud83d\udfe0 Hold",
      "sma200": 13.916850035190583,
      "ema55": 18.324399902701796,
      "ema21": 18.723868270625825,
      "rsi14": 48.584367600658666,
      "atr14_pct": 4.523938771161308,
      "vol_ratio": 0.7334123150543421,
      "ema21_fmt": "\ud83d\udfe0 $18.72",
      "ema55_fmt": "\ud83d\udfe1 $18.32",
      "sma200_fmt": "\ud83d\udfe2 $13.92",
      "vol_fmt": "0.7x",
      "rsi14_fmt": "49",
      "earnings_fmt": "\u26a0\ufe0f 2026-02-26",
      "Day%": NaN,
      "picked_date": "8/15/2025"
    },
    {
      "ticker": "W",
      "last_price": 79.56999969482422,
      "day_change_pct": null,
      "next_earnings": "2026-04-30",
      "quant_score": 3.2,
      "value_grade": "\ud83d\udd34 D-",
      "growth_grade": "\ud83d\udfe2 A+",
      "profitability_grade": "\ud83d\udd34 D",
      "momentum_grade": "\ud83d\udfe2 A",
      "eps_revisions_grade": "\ud83d\udfe1 B",
      "hold_streak_days": 2,
      "ap_rule_action": "",
      "hold_countdown": 178.0,
      "dte": 69,
      "return_pct": -20.438013947534955,
      "company_name": "Consumer Discretionary",
      "quant_rating": "Hold",
      "quant_rating_emoji": "\ud83d\udfe0 Hold",
      "sma200": 102.02114743092021,
      "ema55": 99.39851194477613,
      "ema21": 94.26273757950126,
      "rsi14": 32.36975680320219,
      "atr14_pct": 8.074996380814818,
      "vol_ratio": 2.817727688761951,
      "ema21_fmt": "\ud83d\udd34 $94.26",
      "ema55_fmt": "\ud83d\udd34 $99.40",
      "sma200_fmt": "\ud83d\udd34 $102.02",
      "vol_fmt": "\ud83d\udd25 2.8x",
      "rsi14_fmt": "32",
      "earnings_fmt": "2026-04-30",
      "Day%": NaN,
      "picked_date": "12/1/2025"
    },
    {
      "ticker": "WLDN",
      "last_price": 118.12999725341797,
      "day_change_pct": null,
      "next_earnings": "2026-02-26",
      "quant_score": 4.15,
      "value_grade": "\ud83d\udfe0 C",
      "growth_grade": "\ud83d\udfe2 A-",
      "profitability_grade": "\ud83d\udfe1 B-",
      "momentum_grade": "\ud83d\udfe2 A+",
      "eps_revisions_grade": "\ud83d\udfe0 C",
      "hold_streak_days": 0,
      "ap_rule_action": "",
      "hold_countdown": NaN,
      "dte": 6,
      "return_pct": 11.95441574458246,
      "company_name": "Industrials",
      "quant_rating": "Buy",
      "quant_rating_emoji": "\ud83d\udfe1 Buy",
      "sma200": 92.17860033035278,
      "ema55": 115.0475323985756,
      "ema21": 118.65786596880163,
      "rsi14": 49.465231186172375,
      "atr14_pct": 5.787416633273354,
      "vol_ratio": 0.5474880170424286,
      "ema21_fmt": "\ud83d\udfe0 $118.66",
      "ema55_fmt": "\ud83d\udfe1 $115.05",
      "sma200_fmt": "\ud83d\udfe2 $92.18",
      "vol_fmt": "0.5x",
      "rsi14_fmt": "49",
      "earnings_fmt": "\u26a0\ufe0f 2026-02-26",
      "Day%": NaN,
      "picked_date": "7/1/2025"
    }
  ]
}